volexity/gostrap/__init__.py
volexity/gostrap/_version.py
volexity/gostrap/cli.py
volexity/gostrap/py.typed
volexity/gostrap/sample_generator.py
volexity/gostrap/models/__init__.py
volexity/gostrap/models/arch_types.py
volexity/gostrap/models/cli_arguments.py
volexity/gostrap/models/platform_types.py
gostrap-1.1.2.dist-info/METADATA
gostrap-1.1.2.dist-info/WHEEL
gostrap-1.1.2.dist-info/entry_points.txt
gostrap-1.1.2.dist-info/licenses/LICENSE.md
gostrap-1.1.2.dist-info/RECORD
