Metadata-Version: 2.4
Name: gostrap
Version: 1.1.2
Summary: A tool simplifying the generaton of clean GO sample with a specified set of included libraries.
Project-URL: Documentation, https://gitlab.research.volexity.com/threat-intel/gostrap/-/blob/master/README.md
Project-URL: Issues, https://gitlab.research.volexity.com/threat-intel/gostrap/-/issues
Project-URL: Source, https://gitlab.research.volexity.com/threat-intel/gostrap
Author-email: Killian Raimbaud <kraimbaud@volexity.com>
License-File: LICENSE.md
Classifier: Development Status :: 4 - Beta
Classifier: License :: Other/Proprietary License
Classifier: Programming Language :: Python
Classifier: Programming Language :: Python :: 3.10
Classifier: Programming Language :: Python :: 3.11
Classifier: Programming Language :: Python :: 3.12
Classifier: Programming Language :: Python :: 3.13
Classifier: Programming Language :: Python :: Implementation :: CPython
Classifier: Programming Language :: Python :: Implementation :: PyPy
Requires-Python: >=3.10
Requires-Dist: argparse~=1.4.0
Requires-Dist: gittoolfetcher~=1.2.1
Requires-Dist: multiprocess~=0.70.17
Requires-Dist: yaspin~=3.4.0
